{
    "/js/bundle.js": "/js/bundle.js?id=34c3138523d030493fe8",
    "/css/app.css": "/css/app.css?id=066eacce45481c86e344",
    "/js/users.js": "/js/users.js?id=f2d98a8ef2b83da65922",
    "/js/notification/setup.js": "/js/notification/setup.js?id=7f3b6f2e7090a1b83693",
    "/js/apiClient.js": "/js/apiClient.js?id=81eec678f46a263292d8",
    "/js/vendor.js": "/js/vendor.js?id=d501e90cce266b22eec0",
    "/js/role.js": "/js/role.js?id=4b0d6ad7542830359c9d",
    "/js/registrasi.js": "/js/registrasi.js?id=50c0cdae03c78f065306",
    "/js/notification/history.js": "/js/notification/history.js?id=2edbbbd1621150319369",
    "/js/menu.js": "/js/menu.js?id=c229a7dfbbb58acc73d6",
    "/js/dashboard.js": "/js/dashboard.js?id=9a4d614b1352df9d5631",
    "/js/activity.js": "/js/activity.js?id=ff77eac810cf80fb2f1d",
    "/js/manifest.js": "/js/manifest.js?id=d0e1c8e85afece9d1ddc",
    "/js/themes/plugins/switchery/switchery.js": "/js/themes/plugins/switchery/switchery.js?id=9b950d2e8b99dca4b801"
}